{
    "Main" : {
      "title" : {
        "type" : "StructuredText",
        "config" : {
          "single" : "heading2, heading3, heading4, heading5, heading6",
          "label" : "title",
          "placeholder" : "Digite aqui seu título"
        }
      },
      "post-image" : {
        "type" : "Image",
        "config" : {
          "constraint" : { },
          "thumbnails" : [ ],
          "label" : "post-image"
        }
      },
      "post-text" : {
        "type" : "StructuredText",
        "config" : {
          "multi" : "paragraph, preformatted, heading2, heading3, heading4, heading5, heading6, strong, em, hyperlink, image, embed, list-item, o-list-item, rtl",
          "label" : "post-text",
          "placeholder" : "O texto propriamente dito"
        }
      }
    }
  }